LibreStopping/LibreStopping.py
LibreStopping/__init__.py
LibreStopping-0.1.2.dist-info/LICENSE
LibreStopping-0.1.2.dist-info/METADATA
LibreStopping-0.1.2.dist-info/WHEEL
LibreStopping-0.1.2.dist-info/top_level.txt
LibreStopping-0.1.2.dist-info/RECORD
