Metadata-Version: 2.1
Name: LibreStopping
Version: 0.1.2
Summary: A library for implementing early stopping functionality in LibRecommender models
Author-email: Jurrian van Geresteijn <Jurrian6@gmail.com>
License: MIT
Project-URL: Homepage, https://github.com/GitJvG/LibreStopping
Classifier: Programming Language :: Python :: 3
Classifier: License :: OSI Approved :: MIT License
Classifier: Operating System :: OS Independent
Requires-Python: >=3.6
License-File: LICENSE
